django_graphbox/__init__.py
django_graphbox/apps.py
django_graphbox/builder.py
django_graphbox/constants.py
django_graphbox/exceptions.py
django_graphbox/hasher.py
django_graphbox/models.py
django_graphbox/session.py
django_graphbox/views.py
django_graphbox/helpers/__init__.py
django_graphbox/helpers/middlewares.py
django_graphbox/helpers/mutations.py
django_graphbox/helpers/queries.py
django_graphbox/helpers/sessions.py
django_graphbox/helpers/shared.py
django_graphbox/middleware/__init__.py
django_graphbox/middleware/graphbox_auth.py
django_graphbox/migrations/0001_initial.py
django_graphbox/migrations/0002_alter_logincaptcha_user_id.py
django_graphbox/migrations/__init__.py
django_graphbox-1.5.11.dist-info/licenses/LICENSE
django_graphbox-1.5.11.dist-info/METADATA
django_graphbox-1.5.11.dist-info/WHEEL
django_graphbox-1.5.11.dist-info/top_level.txt
django_graphbox-1.5.11.dist-info/RECORD
