Metadata-Version: 2.4
Name: django_graphbox
Version: 1.5.11
Summary: Package for easy building GraphQL API with Django
Home-page: https://github.com/yefeza/django-graphbox
Author: Yeison Fernandez
Author-email: contacto@90horasporsemana.com
License: MIT
Classifier: Environment :: Web Environment
Classifier: Framework :: Django
Classifier: Intended Audience :: Developers
Classifier: Programming Language :: Python
Classifier: Topic :: Software Development :: Libraries :: Application Frameworks
Requires-Python: >=3.6
License-File: LICENSE
Requires-Dist: Django>=2.2.1
Requires-Dist: graphene-django>=2.15.0
Requires-Dist: pyjwt>=2.3.0
Requires-Dist: urllib3>=1.26.9
Requires-Dist: pillow<10.0.0,>=8.4.0
Dynamic: license-file
